README.md
setup.py
django_db_reconnect/__init__.py
django_db_reconnect.egg-info/PKG-INFO
django_db_reconnect.egg-info/SOURCES.txt
django_db_reconnect.egg-info/dependency_links.txt
django_db_reconnect.egg-info/top_level.txt